Workbook
Name Slicer_Region: #N/A

Sheet Data
B2: Retailer Dataset
B4: Retailer | C4: Retailer ID | D4: Invoice Date | E4: Region | F4: State | G4: City | H4: Beverage Brand | I4: Price per Unit | J4: Units Sold | K4: Total Sales | L4: Operating Profit | M4: Operating Margin
B5: BevCo | C5: 1185732 | D5: 44562 | E5: Northeast | F5: New York | G5: New York | H5: Coca-Cola | I5: 0.5 | J5: 12000 | K5: 6000 | L5: 3000 | M5: 0.5
B6: BevCo | C6: 1185732 | D6: 44563 | E6: Northeast | F6: New York | G6: New York | H6: Diet Coke | I6: 0.5 | J6: 10000 | K6: 5000 | L6: 1500 | M6: 0.3
B7: BevCo | C7: 1185732 | D7: 44564 | E7: Northeast | F7: New York | G7: New York | H7: Sprite | I7: 0.4 | J7: 10000 | K7: 4000 | L7: 1400 | M7: 0.35
B8: BevCo | C8: 1185732 | D8: 44565 | E8: Northeast | F8: New York | G8: New York | H8: Fanta | I8: 0.45 | J8: 8500 | K8: 3825 | L8: 1338.75 | M8: 0.35
B9: BevCo | C9: 1185732 | D9: 44566 | E9: Northeast | F9: New York | G9: New York | H9: Powerade | I9: 0.6 | J9: 9000 | K9: 5400 | L9: 1620 | M9: 0.3
B10: BevCo | C10: 1185732 | D10: 44567 | E10: Northeast | F10: New York | G10: New York | H10: Dasani Water | I10: 0.5 | J10: 10000 | K10: 5000 | L10: 1250 | M10: 0.25
B11: BevCo | C11: 1185732 | D11: 44568 | E11: Northeast | F11: New York | G11: New York | H11: Coca-Cola | I11: 0.5 | J11: 12500 | K11: 6250 | L11: 3125 | M11: 0.5
B12: BevCo | C12: 1185732 | D12: 44569 | E12: Northeast | F12: New York | G12: New York | H12: Diet Coke | I12: 0.5 | J12: 9000 | K12: 4500 | L12: 1350 | M12: 0.3
B13: BevCo | C13: 1185732 | D13: 44582 | E13: Northeast | F13: New York | G13: New York | H13: Sprite | I13: 0.4 | J13: 9500 | K13: 3800 | L13: 1330 | M13: 0.35
B14: BevCo | C14: 1185732 | D14: 44583 | E14: Northeast | F14: New York | G14: New York | H14: Fanta | I14: 0.45 | J14: 8250 | K14: 3712.5 | L14: 1299.375 | M14: 0.35
B15: BevCo | C15: 1185732 | D15: 44584 | E15: Northeast | F15: New York | G15: New York | H15: Powerade | I15: 0.6 | J15: 9000 | K15: 5400 | L15: 1620 | M15: 0.3
B16: BevCo | C16: 1185732 | D16: 44585 | E16: Northeast | F16: New York | G16: New York | H16: Dasani Water | I16: 0.5 | J16: 10000 | K16: 5000 | L16: 1250 | M16: 0.25
... B9652: BevCo | C9652: 1185732 | D9652: 44979 | E9652: Northeast | F9652: New Hampshire | G9652: Manchester | H9652: Sprite | I9652: 0.29 | J9652: 830 | K9652: 240.7 | L9652: 64.989 | M9652: 0.27

Sheet Analyze
A1: KPI's | B1: Total Sales | D1: Total Profit | F1: Total Profit Margin | G1: Average Profit Margin
A6: 1. Display Total and Average Sales of all Retailers
A7: 2. Display Total and Average Sales per Band
A8: 3. Compare Retailers for 2022-2023
B16: Sum of Total Sales | D16: Sum of Operating Profit | F16: Sum of Operating Profit | G16: Average of Operating Margin
B17: 12016665 | D17: 4722496.8 | F17: 4722496.8 | G17: 0.42299129
F22: Average of Operating Profit
F23: 489.47935
G26: Sum of Units Sold
G27: 24788610
G32: Sum of Total Sales | H32: Column Labels
G33: Row Labels | H33: 2022 | I33: 2023
G34: West Soda | H34: 1170361.6 | I34: 2070594.2 | J34: =G34 -> West Soda | K34: =H34 -> 1170361.6 | L34: =I34 -> 2070594.2
G35: Walmart | H35: 339912.5 | I35: 580211 | J35: =G35 -> Walmart | K35: =H35 -> 339912.5 | L35: =I35 -> 580211
G36: Target | H36: 9250.3 | I36: 1341995 | J36: =G36 -> Target | K36: =H36 -> 9250.3 | L36: =I36 -> 1341995
G37: FizzyCo | H37: 161210.1 | I37: 2262827.1 | J37: =G37 -> FizzyCo | K37: =H37 -> 161210.1 | L37: =I37 -> 2262827.1
G38: BevCo | H38: 466788 | I38: 2327606.5 | J38: =G38 -> BevCo | K38: =H38 -> 466788 | L38: =I38 -> 2327606.5
G39: Amazon | H39: 276210 | I39: 1009698.7 | J39: =G39 -> Amazon | K39: =H39 -> 276210 | L39: =I39 -> 1009698.7
G45: Sum of Total Sales | H45: Column Labels
G46: Row Labels | H46: 2022 | I46: 2023
G47: Coca-Cola | H47: 30454.6 | I47: 440281.4 | J47: =G47 -> Coca-Cola | K47: =H47 -> 30454.6 | L47: =I47 -> 440281.4
B48: Row Labels | C48: Total Retailer Sales | D48: Average of Operating Profit | G48: Dasani Water | H48: 18117.5 | I48: 327183.3 | J48: =G48 -> Dasani Water | K48: =H48 -> 18117.5 | L48: =I48 -> 327183.3
B49: 2022 | C49: 2423732.5 | D49: 692.43511 | G49: Diet Coke | H49: 14351.2 | I49: 247577.7 | J49: =G49 -> Diet Coke | K49: =H49 -> 14351.2 | L49: =I49 -> 247577.7
B50: Qtr1 | C50: 692776.1 | D50: 648.0737 | G50: Sprite | H50: 10885.2 | I50: 188859.6 | J50: =G50 -> Sprite | K50: =H50 -> 10885.2 | L50: =I50 -> 188859.6
B51: Qtr2 | C51: 644203.9 | D51: 836.18384 | G51: Powerade | H51: 9122.9 | I51: 213255.7 | J51: =G51 -> Powerade | K51: =H51 -> 9122.9 | L51: =I51 -> 213255.7
B52: Qtr3 | C52: 719170.4 | D52: 796.47038 | G52: Fanta | H52: 7460.4 | I52: 159893.9 | J52: =G52 -> Fanta | K52: =H52 -> 7460.4 | L52: =I52 -> 159893.9
B53: Qtr4 | C53: 367582.1 | D53: 484.96658
B54: 2023 | C54: 9592932.5 | D54: 457.81767
B55: Qtr1 | C55: 1877584.3 | D55: 348.13157
B56: Qtr2 | C56: 2379424.8 | D56: 452.75746
B57: Qtr3 | C57: 2805752.5 | D57: 539.54722
B58: Qtr4 | C58: 2530170.9 | D58: 487.66769
B59: Grand Total | C59: 12016665 | D59: 489.47935
B63: Qtr1 | C63: 692776.1 | D63: 648.0737
B64: Qtr2 | C64: 644203.9 | D64: 836.18384
B65: Qtr3 | C65: 719170.4 | D65: 796.47038
B66: Qtr4 | C66: 367582.1 | D66: 484.96658
B67: Qtr1 | C67: 1877584.3 | D67: 348.13157
... B70: Qtr4 | C70: 2530170.9 | D70: 487.66769

Sheet Dashboard
B16: BRAND | C16: SALES 2022 | D16: SALES 2022 | E16: VARIANCE | H16: RETAILER | I16: SALES 2022 | J16: SALES 2023 | K16: VARIANCE
B17: =Analyze!J34 -> West Soda | C17: =Analyze!K34 -> 1170361.6 | D17: =Analyze!L34 -> 2070594.2 | E17: =D17-C17 -> 900232.6 | H17: =Analyze!J47 -> Coca-Cola | I17: =Analyze!K47 -> 30454.6 | J17: =Analyze!L47 -> 440281.4 | K17: =J17-I17 -> 409826.8
B18: =Analyze!J35 -> Walmart | C18: =Analyze!K35 -> 339912.5 | D18: =Analyze!L35 -> 580211 | E18: =D18-C18 -> 240298.5 | H18: =Analyze!J48 -> Dasani Water | I18: =Analyze!K48 -> 18117.5 | J18: =Analyze!L48 -> 327183.3 | K18: =J18-I18 -> 309065.8
B19: =Analyze!J36 -> Target | C19: =Analyze!K36 -> 9250.3 | D19: =Analyze!L36 -> 1341995 | E19: =D19-C19 -> 1332744.7 | H19: =Analyze!J49 -> Diet Coke | I19: =Analyze!K49 -> 14351.2 | J19: =Analyze!L49 -> 247577.7 | K19: =J19-I19 -> 233226.5
B20: =Analyze!J37 -> FizzyCo | C20: =Analyze!K37 -> 161210.1 | D20: =Analyze!L37 -> 2262827.1 | E20: =D20-C20 -> 2101617 | H20: =Analyze!J50 -> Sprite | I20: =Analyze!K50 -> 10885.2 | J20: =Analyze!L50 -> 188859.6 | K20: =J20-I20 -> 177974.4
B21: =Analyze!J38 -> BevCo | C21: =Analyze!K38 -> 466788 | D21: =Analyze!L38 -> 2327606.5 | E21: =D21-C21 -> 1860818.5 | H21: =Analyze!J51 -> Powerade | I21: =Analyze!K51 -> 9122.9 | J21: =Analyze!L51 -> 213255.7 | K21: =J21-I21 -> 204132.8
B22: =Analyze!J39 -> Amazon | C22: =Analyze!K39 -> 276210 | D22: =Analyze!L39 -> 1009698.7 | E22: =D22-C22 -> 733488.7 | H22: =Analyze!J52 -> Fanta | I22: =Analyze!K52 -> 7460.4 | J22: =Analyze!L52 -> 159893.9 | K22: =J22-I22 -> 152433.5
